rocore/__init__.py
rocore/caching.py
rocore/diagnostics.py
rocore/exceptions.py
rocore/folders.py
rocore/json.py
rocore/meta.py
rocore/models.py
rocore/registry.py
rocore/decorators/__init__.py
rocore/decorators/logs.py
rocore/decorators/retry.py
rocore/typesutils/__init__.py
rocore/typesutils/dateutils.py
rocore/typesutils/timeutils.py
rocore-1.0.8.dist-info/LICENSE
rocore-1.0.8.dist-info/METADATA
rocore-1.0.8.dist-info/WHEEL
rocore-1.0.8.dist-info/top_level.txt
rocore-1.0.8.dist-info/RECORD
