Metadata-Version: 2.1
Name: rocore
Version: 1.0.8
Summary: Core classes and functions, reusable in any kind of Python application
Home-page: https://github.com/RobertoPrevato/rocore
Author: RobertoPrevato
Author-email: roberto.prevato@gmail.com
License: MIT
Keywords: core utilities
Platform: UNKNOWN
Classifier: Development Status :: 5 - Production/Stable
Classifier: License :: OSI Approved :: MIT License
Classifier: Programming Language :: Python :: 3
Classifier: Operating System :: OS Independent
